selenious/__init__.py
selenious/decorators.py
selenious/helpers.py
selenious/recover.py
selenious/webdriver.py
selenious/webdriver_mixin.py
selenious/webelement.py
tests/__init__.py
tests/integration.py
tests/mock_webdriver.py
tests/test_import_webdriver.py
tests/test_webdriver.py
tests/test_webelement.py
tests/snapshots/__init__.py
tests/snapshots/snap_test_webdriver.py
tests/snapshots/snap_test_webelement.py
selenious-0.2.1.dist-info/AUTHORS.rst
selenious-0.2.1.dist-info/LICENSE.txt
selenious-0.2.1.dist-info/METADATA
selenious-0.2.1.dist-info/WHEEL
selenious-0.2.1.dist-info/top_level.txt
selenious-0.2.1.dist-info/RECORD
