Metadata-Version: 2.1
Name: selenious
Version: 0.2.1
Summary: Enhancement to Selenium WebDriver for timeouts and more.
Home-page: https://github.com/bonafideduck/selenious
Author: Mark Eklund
Author-email: selenious@patnan.com
License: MIT
Download-URL: https://pypi.org/project/selenious/
Keywords: Selenium,WebDriver,timeout
Platform: UNKNOWN
License-File: LICENSE.txt
License-File: AUTHORS.rst
Requires-Dist: selenium
